tornado_xstatic.py
tornado_xstatic-0.3.dist-info/LICENSE
tornado_xstatic-0.3.dist-info/WHEEL
tornado_xstatic-0.3.dist-info/METADATA
tornado_xstatic-0.3.dist-info/RECORD
