Metadata-Version: 2.1
Name: tornado_xstatic
Version: 0.3
Summary: Utilities for using XStatic in Tornado applications
Author-email: Thomas Kluyver <thomas@kluyver.me.uk>
Requires-Python: >= 3.4
Classifier: License :: OSI Approved :: BSD License
Classifier: Environment :: Web Environment
Classifier: Programming Language :: Python :: 2
Classifier: Programming Language :: Python :: 3
Classifier: Topic :: Internet :: WWW/HTTP :: HTTP Servers
Requires-Dist: tornado
Project-URL: Home, https://github.com/takluyver/tornado_xstatic
